ratio_delta/__init__.py
ratio_delta-1.0.2.dist-info/METADATA
ratio_delta-1.0.2.dist-info/WHEEL
ratio_delta-1.0.2.dist-info/licenses/COPYING
ratio_delta-1.0.2.dist-info/licenses/COPYING.LESSER
ratio_delta-1.0.2.dist-info/RECORD
