Metadata-Version: 2.3
Name: ratio-delta
Version: 1.0.2
Summary: Add functions for variants of a common arithmetic operation
Project-URL: Homepage, https://github.com/LLyaudet/RatioDelta
Project-URL: Bug Tracker, https://github.com/LLyaudet/RatioDelta/issues
Author-email: Laurent Lyaudet <laurent.lyaudet@gmail.com>
Maintainer-email: Laurent Lyaudet <laurent.lyaudet@gmail.com>
License:                    GNU LESSER GENERAL PUBLIC LICENSE
License-File: COPYING
License-File: COPYING.LESSER
Keywords: Python,fused-divide-add,fused-divide-decrement,fused-divide-increment,fused-divide-subract,ratio-alpha,ratio-delta,ratio-iota,ratio-sigma
Classifier: Development Status :: 5 - Production/Stable
Classifier: Intended Audience :: Developers
Classifier: License :: OSI Approved :: GNU Lesser General Public License v3 or later (LGPLv3+)
Classifier: Operating System :: OS Independent
Classifier: Programming Language :: Python
Classifier: Programming Language :: Python :: 3
Classifier: Topic :: Software Development :: Libraries :: Python Modules
Classifier: Typing :: Typed
Requires-Python: >=3.5
Provides-Extra: dev
Requires-Dist: black; extra == 'dev'
Requires-Dist: isort; extra == 'dev'
Requires-Dist: mypy; extra == 'dev'
Requires-Dist: pylint; extra == 'dev'
